backlash/__init__.py
backlash/_compat.py
backlash/console.py
backlash/debug.py
backlash/frtools.py
backlash/repr.py
backlash/tbtools.py
backlash/utils.py
backlash/statics/FONT_LICENSE
backlash/statics/console.png
backlash/statics/debugger.js
backlash/statics/jquery.js
backlash/statics/less.png
backlash/statics/more.png
backlash/statics/opensans.ttf
backlash/statics/source.png
backlash/statics/style.css
backlash/trace_errors/__init__.py
backlash/trace_errors/sentry.py
backlash/tracing/__init__.py
backlash/tracing/errors/__init__.py
backlash/tracing/errors/middleware.py
backlash/tracing/reporters/__init__.py
backlash/tracing/reporters/mail.py
backlash/tracing/reporters/sentry.py
backlash/tracing/slowrequests/__init__.py
backlash/tracing/slowrequests/middleware.py
backlash/tracing/slowrequests/timer.py
backlash-0.4.0.dist-info/licenses/AUTHORS
backlash-0.4.0.dist-info/licenses/LICENSE
backlash-0.4.0.dist-info/METADATA
backlash-0.4.0.dist-info/WHEEL
backlash-0.4.0.dist-info/top_level.txt
backlash-0.4.0.dist-info/RECORD
