Metadata-Version: 2.4
Name: backlash
Version: 0.4.0
Summary: Standalone WebOb port of the Werkzeug Debugger with Python3 support meant to replace WebError in TurboGears2
Author-email: Alessandro Molina <alessandro@molina.fyi>
License-Expression: MIT
Project-URL: Homepage, https://github.com/TurboGears/backlash
Keywords: wsgi,debugger,webob,python3,web
Classifier: Intended Audience :: Developers
Classifier: Programming Language :: Python
Classifier: Programming Language :: Python :: 3
Classifier: Topic :: Internet :: WWW/HTTP :: WSGI :: Middleware
Classifier: Topic :: Internet :: WWW/HTTP :: WSGI
License-File: LICENSE
License-File: AUTHORS
Requires-Dist: WebOb
Dynamic: license-file
